dkdc_state/__init__.py
dkdc_state/main.py
dkdc_state-0.0.6.dist-info/METADATA
dkdc_state-0.0.6.dist-info/WHEEL
dkdc_state-0.0.6.dist-info/top_level.txt
dkdc_state-0.0.6.dist-info/RECORD
