Metadata-Version: 2.1
Name: dkdc-state
Version: 0.0.6
Summary: manage state
Author-email: Cody <cody@dkdc.dev>
Project-URL: Homepage, https://github.com/dkdc-io/dkdc-state
Project-URL: Bug Tracker, https://github.com/dkdc-io/dkdc-state/issues
Classifier: Programming Language :: Python :: 3
Classifier: License :: OSI Approved :: MIT License
Classifier: Operating System :: OS Independent
Requires-Python: >=3.12
Requires-Dist: ibis-framework[duckdb,sqlite]
Provides-Extra: dev
Requires-Dist: ruff; extra == "dev"
Requires-Dist: ipython; extra == "dev"
Requires-Dist: jupyter; extra == "dev"
Requires-Dist: nbclient; extra == "dev"
Requires-Dist: ipykernel; extra == "dev"
Provides-Extra: test
Requires-Dist: pytest; extra == "test"
Provides-Extra: postgres
Requires-Dist: ibis-framework[postgres]; extra == "postgres"
